allure_client/__init__.py
allure_client/api_client.py
allure_client/api_response.py
allure_client/configuration.py
allure_client/exceptions.py
allure_client/py.typed
allure_client/rest.py
allure_client/api/__init__.py
allure_client/api/access_group_bulk_controller_api.py
allure_client/api/access_group_controller_api.py
allure_client/api/account_admin_controller_api.py
allure_client/api/account_management_bulk_controller_api.py
allure_client/api/account_management_controller_api.py
allure_client/api/account_user_controller_api.py
allure_client/api/admin_misc_controller_api.py
allure_client/api/analytic_controller_api.py
allure_client/api/api_token_controller_api.py
allure_client/api/async_job_controller_api.py
allure_client/api/authentication_controller_api.py
allure_client/api/blob_storage_controller_api.py
allure_client/api/blob_storage_upgrade_controller_api.py
allure_client/api/business_metric_controller_api.py
allure_client/api/category_controller_api.py
allure_client/api/category_matcher_controller_api.py
allure_client/api/cleaner_schema_controller_api.py
allure_client/api/cleanup_controller_api.py
allure_client/api/comment_controller_api.py
allure_client/api/custom_field_bulk_controller_api.py
allure_client/api/custom_field_controller_api.py
allure_client/api/custom_field_project_controller_api.py
allure_client/api/custom_field_project_controller_v2_api.py
allure_client/api/custom_field_schema_controller_api.py
allure_client/api/custom_field_value_bulk_controller_api.py
allure_client/api/custom_field_value_controller_api.py
allure_client/api/custom_field_value_project_controller_api.py
allure_client/api/dashboard_controller_api.py
allure_client/api/dashboard_template_controller_api.py
allure_client/api/defect_bulk_controller_api.py
allure_client/api/defect_controller_api.py
allure_client/api/defect_matcher_controller_api.py
allure_client/api/env_var_controller_api.py
allure_client/api/env_var_schema_controller_api.py
allure_client-1.0.2.dist-info/METADATA
allure_client-1.0.2.dist-info/WHEEL
allure_client-1.0.2.dist-info/top_level.txt
allure_client-1.0.2.dist-info/RECORD
